.gitignore
CHANGES.rst
LICENSE.txt
README.rst
bootstrap.py
buildout.cfg
setup.py
js/__init__.py
js.respond.egg-info/PKG-INFO
js.respond.egg-info/SOURCES.txt
js.respond.egg-info/dependency_links.txt
js.respond.egg-info/entry_points.txt
js.respond.egg-info/namespace_packages.txt
js.respond.egg-info/not-zip-safe
js.respond.egg-info/requires.txt
js.respond.egg-info/top_level.txt
js/respond/__init__.py
js/respond/test_respond.js.txt
js/respond/resources/respond.min.js
js/respond/resources/respond.src.js