Metadata-Version: 1.0
Name: js.respond
Version: 1.2.0
Summary: Fanstatic packaging of Respond.js
Home-page: UNKNOWN
Author: Fanstatic Developers
Author-email: fanstatic@googlegroups.com
License: BSD
Platform: UNKNOWN
